DBN/__init__.py
DBN/main.py
DBN/node.py
DBN-0.1.0.dist-info/LICENSE
DBN-0.1.0.dist-info/METADATA
DBN-0.1.0.dist-info/WHEEL
DBN-0.1.0.dist-info/entry_points.txt
DBN-0.1.0.dist-info/top_level.txt
DBN-0.1.0.dist-info/RECORD
